ros2_object_detection/__init__.py
ros2_object_detection/ros2_object_detection.py
ros2_object_detection-1.0.4.dist-info/LICENSE.txt
ros2_object_detection-1.0.4.dist-info/LICENSE.txtZone.Identifier
ros2_object_detection-1.0.4.dist-info/METADATA
ros2_object_detection-1.0.4.dist-info/WHEEL
ros2_object_detection-1.0.4.dist-info/top_level.txt
ros2_object_detection-1.0.4.dist-info/RECORD
